aiolava/__init__.py
aiolava/base_client.py
aiolava/business_client.py
aiolava/misc.py
aiolava/wallet_client.py
aiolava/endpoints/__init__.py
aiolava/endpoints/base.py
aiolava/endpoints/business/__init__.py
aiolava/endpoints/business/check_invoice_status.py
aiolava/endpoints/business/create_invoice.py
aiolava/endpoints/wallet/__init__.py
aiolava/endpoints/wallet/create_invoice.py
aiolava/endpoints/wallet/invoice_info.py
aiolava/endpoints/wallet/ping.py
aiolava/endpoints/wallet/wallet_list.py
aiolava/types/__init__.py
aiolava/types/base.py
aiolava/types/business/__init__.py
aiolava/types/business/check_invoice_status.py
aiolava/types/business/create_invoice.py
aiolava/types/wallet/__init__.py
aiolava/types/wallet/create_invoice.py
aiolava/types/wallet/invoice_info.py
aiolava/types/wallet/ping.py
aiolava/types/wallet/wallet_list.py
aiolavapy-0.1.2.dist-info/LICENSE
aiolavapy-0.1.2.dist-info/METADATA
aiolavapy-0.1.2.dist-info/WHEEL
aiolavapy-0.1.2.dist-info/top_level.txt
aiolavapy-0.1.2.dist-info/RECORD
