Metadata-Version: 2.1
Name: aiolavapy
Version: 0.1.2
Summary: Async library for Lava API
Home-page: https://github.com/DTPlayer/aiolava
Author: reff06
Author-email: info@dnsprovider.tech
Project-URL: Official documentation, https://dev.lava.ru/
Keywords: lava aiolava lavaapi
Classifier: Programming Language :: Python :: 3.11
Classifier: License :: OSI Approved :: MIT License
Classifier: Operating System :: OS Independent
Requires-Python: >=3.10
License-File: LICENSE
Requires-Dist: aiohttp >=3.9.1
Requires-Dist: pydantic >=2.0.2
